hkmConfig/BaseConfig.py
hkmConfig/ConfigSystemInterfaces.py
hkmConfig/Helpers/ConfigHelper.py
hkmConfig/HkmCode_hkmConfig.egg-info/PKG-INFO
hkmConfig/HkmCode_hkmConfig.egg-info/SOURCES.txt
hkmConfig/HkmCode_hkmConfig.egg-info/dependency_links.txt
hkmConfig/HkmCode_hkmConfig.egg-info/top_level.txt
hkmConfig/Hkm_Bin/App.py
hkmConfig/NamespaceHelpers.py
hkmConfig/__init__.py
hkmConfig/__main__.py
hkmConfig/yamlConfig/YamlParse.py
hkmcodepy_hkmconfig-0.0.2.dist-info/LICENSE
hkmcodepy_hkmconfig-0.0.2.dist-info/WHEEL
hkmcodepy_hkmconfig-0.0.2.dist-info/METADATA
hkmcodepy_hkmconfig-0.0.2.dist-info/RECORD
