Metadata-Version: 2.1
Name: hkmcodepy-hkmconfig
Version: 0.0.2
Summary: @HkmCodePy Configuration system package
Home-page: https://github.com/hakrichTech/HkmCodePy
License: GNU
Keywords: python,import,HkmCodePy,config,HkmCodePy-hkmConfig,metaprogramming,dynamic config,configuration
Author: Hakeem Shamavu
Author-email: hakeemshamavu@hakrichteam.com
Maintainer: Hakeem Shamavu
Maintainer-email: hakeemshamavu@hakrichteam.com
Requires-Python: >=3.7,<4.0
Classifier: Development Status :: 1 - Planning
Classifier: Intended Audience :: Developers
Classifier: License :: OSI Approved :: MIT License
Classifier: License :: Other/Proprietary License
Classifier: Programming Language :: Python
Classifier: Programming Language :: Python :: 3
Classifier: Programming Language :: Python :: 3.10
Classifier: Programming Language :: Python :: 3.7
Classifier: Programming Language :: Python :: 3.8
Classifier: Programming Language :: Python :: 3.9
Classifier: Programming Language :: Python :: Implementation :: CPython
Classifier: Programming Language :: Python :: Implementation :: PyPy
Classifier: Topic :: Software Development :: Libraries
Project-URL: Documentation, https://github.com/hakrichTech/HkmCodePy
Project-URL: Repository, https://github.com/hakrichTech/HkmCodePy
